telegram_stars_rates/__init__.py
telegram_stars_rates/analyzer.py
telegram_stars_rates/cli.py
telegram_stars_rates-1.0.0.dist-info/licenses/LICENSE
telegram_stars_rates-1.0.0.dist-info/METADATA
telegram_stars_rates-1.0.0.dist-info/WHEEL
telegram_stars_rates-1.0.0.dist-info/entry_points.txt
telegram_stars_rates-1.0.0.dist-info/top_level.txt
telegram_stars_rates-1.0.0.dist-info/RECORD
