Metadata-Version: 2.4
Name: telegram-stars-rates
Version: 1.0.0
Summary: Real-time Telegram Stars to USDT exchange rates via Fragment blockchain
Home-page: https://github.com/telegram-stars/rates
Author: Telegram Stars Team
Author-email: Telegram Stars Team <dev@telegram-stars.com>
Maintainer-email: Telegram Stars Team <dev@telegram-stars.com>
License: MIT
Project-URL: Homepage, https://github.com/telegram-stars/rates
Project-URL: Documentation, https://github.com/telegram-stars/rates#readme
Project-URL: Repository, https://github.com/telegram-stars/rates.git
Project-URL: Bug Tracker, https://github.com/telegram-stars/rates/issues
Project-URL: Changelog, https://github.com/telegram-stars/rates/releases
Project-URL: Web Converter, https://telegram-stars.github.io/rates
Keywords: telegram,stars,ton,fragment,cryptocurrency,exchange,rates,blockchain,usdt,converter
Classifier: Development Status :: 5 - Production/Stable
Classifier: Intended Audience :: Developers
Classifier: Intended Audience :: Financial and Insurance Industry
Classifier: License :: OSI Approved :: MIT License
Classifier: Operating System :: OS Independent
Classifier: Programming Language :: Python :: 3
Classifier: Programming Language :: Python :: 3.7
Classifier: Programming Language :: Python :: 3.8
Classifier: Programming Language :: Python :: 3.9
Classifier: Programming Language :: Python :: 3.10
Classifier: Programming Language :: Python :: 3.11
Classifier: Programming Language :: Python :: 3.12
Classifier: Topic :: Office/Business :: Financial
Classifier: Topic :: Software Development :: Libraries :: Python Modules
Classifier: Typing :: Typed
Requires-Python: >=3.7
License-File: LICENSE
Requires-Dist: requests>=2.25.0
Dynamic: author
Dynamic: home-page
Dynamic: license-file
Dynamic: requires-python
